faspy/__init__.py
faspy/numbatest_df.py
faspy/numbatest_generate_fulldf.py
faspy/test_HQLA.py
faspy/test_bucket.py
faspy/test_buckets.py
faspy/test_cf_alloc.py
faspy/test_createstructures.py
faspy/test_customfix_structures.py
faspy/test_customfloat_structures.py
faspy/test_df_zspread.py
faspy/test_discount_factor_gen.py
faspy/test_fixbond.py
faspy/test_fixleg.py
faspy/test_fixloan.py
faspy/test_floatbond.py
faspy/test_floatleg.py
faspy/test_interpolation.py
faspy/test_loans.py
faspy/test_numba.py
faspy/test_prob_default.py
faspy/basel/__init__.py
faspy/basel/credit/__init__.py
faspy/basel/credit/credit.py
faspy/basel/liquidity/__init__.py
faspy/basel/liquidity/buckets.py
faspy/basel/liquidity/conventions.py
faspy/basel/liquidity/hqla.py
faspy/basel/liquidity/rmp_dates.py
faspy/interestrate/__init__.py
faspy/interestrate/bondclass.py
faspy/interestrate/bonds.py
faspy/interestrate/bonds_jit.py
faspy/interestrate/conventions.py
faspy/interestrate/discount_curve.py
faspy/interestrate/fas_ircls.py
faspy/interestrate/fixincome.py
faspy/interestrate/rmp_bhelp.py
faspy/interestrate/rmp_curves.py
faspy/interestrate/rmp_dates.py
faspy/interestrate/rmp_solvers.py
faspy/interestrate/rmp_stats.py
faspy/risk/__init__.py
faspy/risk/var_utils.py
faspy/risk/var_utils2.py
faspy2-0.0.96.dist-info/LICENSE
faspy2-0.0.96.dist-info/METADATA
faspy2-0.0.96.dist-info/WHEEL
faspy2-0.0.96.dist-info/top_level.txt
faspy2-0.0.96.dist-info/RECORD
